coinpaprika_async_client/__init__.py
coinpaprika_async_client/__version__.py
coinpaprika_async_client/client/__init__.py
coinpaprika_async_client/client/coinpaprika_async_client.py
coinpaprika_async_client/coins/__init__.py
coinpaprika_async_client/coins/api.py
coinpaprika_async_client/coins/models.py
coinpaprika_async_client/exchanges/__init__.py
coinpaprika_async_client/exchanges/api.py
coinpaprika_async_client/exchanges/models.py
coinpaprika_async_client/key/__init__.py
coinpaprika_async_client/key/api.py
coinpaprika_async_client/key/models.py
coinpaprika_async_client/market/__init__.py
coinpaprika_async_client/market/api.py
coinpaprika_async_client/market/models.py
coinpaprika_async_client/misc/__init__.py
coinpaprika_async_client/misc/api.py
coinpaprika_async_client/misc/models.py
coinpaprika_async_client/networking_layer/__init__.py
coinpaprika_async_client/networking_layer/http_async_client.py
coinpaprika_async_client/networking_layer/http_models.py
coinpaprika_async_client/people/__init__.py
coinpaprika_async_client/people/api.py
coinpaprika_async_client/people/models.py
coinpaprika_async_client/shared/__init__.py
coinpaprika_async_client/shared/models.py
coinpaprika_async_client/tags/__init__.py
coinpaprika_async_client/tags/api.py
coinpaprika_async_client/tags/models.py
coinpaprika_async_client/tickers/__init__.py
coinpaprika_async_client/tickers/api.py
coinpaprika_async_client/tickers/models.py
coinpaprika_async-3.1.3.dist-info/LICENSE
coinpaprika_async-3.1.3.dist-info/METADATA
coinpaprika_async-3.1.3.dist-info/WHEEL
coinpaprika_async-3.1.3.dist-info/RECORD
