Metadata-Version: 2.1
Name: coinpaprika-async
Version: 3.1.3
Summary: An asynchronous library for interacting with the Coinpaprika.com API, written with httpx in Python.
Author: DroidZed
Author-email: 41507665+DroidZed@users.noreply.github.com
Requires-Python: >=3.11,<4.0
Classifier: Programming Language :: Python :: 3
Classifier: Programming Language :: Python :: 3.11
Classifier: Programming Language :: Python :: 3.12
Requires-Dist: httpx[http2] (>=0.27.0,<0.28.0)
